Metadata-Version: 2.1
Name: bpmn-tools
Version: 0.10.1
Summary: a collection of tools to work with BPMN
Home-page: https://github.com/christophevg/bpmn-tools
Author: Christophe VG
License: MIT
Keywords: bpmn tools
Platform: UNKNOWN
Classifier: Development Status :: 4 - Beta
Classifier: Intended Audience :: Developers
Classifier: Programming Language :: Python :: 3
Classifier: Programming Language :: Python :: 3.8
Classifier: Programming Language :: Python :: 3.9
Classifier: Programming Language :: Python :: 3.10
Classifier: Programming Language :: Python :: 3.11
Requires-Dist: fire
Requires-Dist: xmltodict
Requires-Dist: colorama
Requires-Dist: graphviz
